LICENSE
README.md
setup.py
RabbitmqPulsar/Connections.py
RabbitmqPulsar/Services.py
RabbitmqPulsar/__init__.py
mq_fw.egg-info/PKG-INFO
mq_fw.egg-info/SOURCES.txt
mq_fw.egg-info/dependency_links.txt
mq_fw.egg-info/requires.txt
mq_fw.egg-info/top_level.txt
pulsar_mq/Clients.py
pulsar_mq/ConsumerType.py
pulsar_mq/Consumers.py
pulsar_mq/Producers.py
pulsar_mq/Schema.py
pulsar_mq/Services.py
pulsar_mq/__init__.py
rabbitmq/Connections.py
rabbitmq/Consumers.py
rabbitmq/Producers.py
rabbitmq/Services.py
rabbitmq/__init__.py