Metadata-Version: 2.1
Name: mq-fw
Version: 2.3.5
Summary: A message queue framework, including pulsar and rabbitmq
Home-page: https://gitee.com/maxbanana
Author: hongbo liu
Author-email: 782027465@qq.com
License: Apache
Platform: UNKNOWN
Classifier: Programming Language :: Python :: 3
Classifier: License :: OSI Approved :: Apache Software License
Classifier: Operating System :: OS Independent
Requires-Python: >=3.6
License-File: LICENSE
